<settings>
  <!--This sends everything else to /public -->
  <mirrors>
    <mirror>
      <id>nexus</id>
      <mirrorOf>external:*</mirrorOf>
      <url>http://nexus/content/groups/public</url>
    </mirror>
  </mirrors>

  <!-- lets disable the download progress indicator that fills up logs -->
  <interactiveMode>false</interactiveMode>

  <servers>
    <server>
      <id>local-nexus</id>
      <username>admin</username>
      <password>admin123</password>
    </server>
    <server>
      <id>nexus</id>
      <username>admin</username>
      <password>admin123</password>
    </server>
    <server>
      <id>oss-sonatype-staging</id>
      <username></username>
      <password></password>
    </server>
  </servers>

  <profiles>
    <profile>
      <id>nexus</id>
      <properties>
        <altDeploymentRepository>local-nexus::default::http://nexus/content/repositories/snapshots/</altDeploymentRepository>
        <altReleaseDeploymentRepository>local-nexus::default::http://nexus/content/repositories/staging/</altReleaseDeploymentRepository>
        <altSnapshotDeploymentRepository>local-nexus::default::http://nexus/content/repositories/snapshots/</altSnapshotDeploymentRepository>
      </properties>
      <repositories>
        <repository>
          <id>central</id>
          <url>http://central</url>
          <releases><enabled>true</enabled></releases>
          <snapshots><enabled>true</enabled></snapshots>
        </repository>
      </repositories>
     <pluginRepositories>
        <pluginRepository>
          <id>central</id>
          <url>http://central</url>
          <releases><enabled>true</enabled></releases>
          <snapshots><enabled>true</enabled></snapshots>
        </pluginRepository>
      </pluginRepositories>
    </profile>
    <profile>
      <id>release</id>
      <properties>
        <gpg.executable>gpg</gpg.executable>
        <gpg.passphrase>${env.GPG_PASSPHRASE}</gpg.passphrase>
      </properties>
    </profile>
  </profiles>
  <activeProfiles>
    <!--make the profile active all the time -->
    <activeProfile>nexus</activeProfile>
  </activeProfiles>
</settings>
